tcb_sheet_tools/__init__.py
tcb_sheet_tools-0.0.0.2.dist-info/LICENSE
tcb_sheet_tools-0.0.0.2.dist-info/METADATA
tcb_sheet_tools-0.0.0.2.dist-info/WHEEL
tcb_sheet_tools-0.0.0.2.dist-info/entry_points.txt
tcb_sheet_tools-0.0.0.2.dist-info/top_level.txt
tcb_sheet_tools-0.0.0.2.dist-info/RECORD
