Metadata-Version: 2.1
Name: tcb-sheet-tools
Version: 0.0.0.2
Summary: A Collection of Utilities. Not even can be described.
Home-page: https://github.com/tomneto
Author: Elemental Tools - Tom Neto
Author-email: info@tomneto.com
License: MIT
License-File: LICENSE
Requires-Dist: pillow
Requires-Dist: imagehash
Requires-Dist: python-Levenshtein
Requires-Dist: fuzzywuzzy
Requires-Dist: langdetect
Requires-Dist: deep-translator
Requires-Dist: nltk
Requires-Dist: pydantic[email]
Requires-Dist: SpeechRecognition
Requires-Dist: icecream
Requires-Dist: spacy
Requires-Dist: selenium
Requires-Dist: pymongo
Requires-Dist: python-dotenv
Requires-Dist: annotated-types
Requires-Dist: antiorm
Requires-Dist: anyio
Requires-Dist: attrs
Requires-Dist: certifi
Requires-Dist: charset-normalizer
Requires-Dist: click
Requires-Dist: cloudant
Requires-Dist: exceptiongroup
Requires-Dist: fastapi
Requires-Dist: greenlet
Requires-Dist: h11
Requires-Dist: idna
Requires-Dist: numpy
Requires-Dist: outcome
Requires-Dist: packaging
Requires-Dist: pandas
Requires-Dist: pip
Requires-Dist: playwright
Requires-Dist: pydantic-core
Requires-Dist: pydantic
Requires-Dist: pyee
Requires-Dist: PySocks
Requires-Dist: python-dateutil
Requires-Dist: pytz
Requires-Dist: requests
Requires-Dist: setuptools
Requires-Dist: six
Requires-Dist: sniffio
Requires-Dist: sortedcontainers
Requires-Dist: trio-websocket
Requires-Dist: trio
Requires-Dist: typing-extensions
Requires-Dist: tzdata
Requires-Dist: urllib3
Requires-Dist: uvicorn
Requires-Dist: webdriver-manager
Requires-Dist: wheel
Requires-Dist: wsproto
Requires-Dist: google-api-python-client
Requires-Dist: google-auth-httplib2
Requires-Dist: google-auth-oauthlib
